backtracking_llm/__init__.py
backtracking_llm/chat.py
backtracking_llm/decision.py
backtracking_llm/generation.py
backtracking_llm/_scripts/__init__.py
backtracking_llm/_scripts/benchmark.py
backtracking_llm/_scripts/cli.py
backtracking_llm/_scripts/train_rl.py
backtracking_llm/_scripts/ui.py
backtracking_llm/benchmark/__init__.py
backtracking_llm/benchmark/config.py
backtracking_llm/benchmark/evaluator.py
backtracking_llm/benchmark/hpo.py
backtracking_llm/benchmark/model.py
backtracking_llm/benchmark/runner.py
backtracking_llm/rl/__init__.py
backtracking_llm/rl/config.py
backtracking_llm/rl/data.py
backtracking_llm/rl/env.py
backtracking_llm/rl/features.py
backtracking_llm/rl/judges.py
backtracking_llm/rl/operators.py
backtracking_llm/rl/rewards.py
backtracking_llm/rl/trainers.py
backtracking_llm/rl/wrapper.py
backtracking_llm-0.3.0.dist-info/METADATA
backtracking_llm-0.3.0.dist-info/WHEEL
backtracking_llm-0.3.0.dist-info/entry_points.txt
backtracking_llm-0.3.0.dist-info/licenses/LICENSE
backtracking_llm-0.3.0.dist-info/RECORD
