Metadata-Version: 2.4
Name: backtracking-llm
Version: 0.3.0
Summary: Library for running inference on large language models with the ability to remove generated tokens.
Project-URL: Homepage, https://github.com/matee8/backtracking_llm
Project-URL: Repository, https://github.com/matee8/backtracking_llm
Project-URL: Issues, https://github.com/matee8/backtracking_llm/issues
Author-email: matee8 <graves-bluff-pesky@duck.com>
License-Expression: MIT
License-File: LICENSE
Keywords: machine-learning,neural-network,text-generation
Classifier: Development Status :: 5 - Production/Stable
Classifier: Intended Audience :: Developers
Classifier: Intended Audience :: Science/Research
Classifier: Natural Language :: English
Classifier: Operating System :: OS Independent
Classifier: Programming Language :: Python
Classifier: Programming Language :: Python :: 3
Classifier: Programming Language :: Python :: 3.9
Classifier: Programming Language :: Python :: 3.10
Classifier: Programming Language :: Python :: 3.11
Classifier: Programming Language :: Python :: 3.12
Classifier: Programming Language :: Python :: 3.13
Classifier: Programming Language :: Python :: Implementation :: CPython
Classifier: Topic :: Scientific/Engineering :: Artificial Intelligence
Classifier: Topic :: Software Development :: Libraries :: Python Modules
Classifier: Topic :: Text Processing :: Linguistic
Requires-Python: >=3.9
Requires-Dist: numpy<3.0.0,>=2.0.1
Requires-Dist: torch<3.0.0,>=2.1.2
Requires-Dist: transformers<5.0.0,>=4.51.3
Provides-Extra: benchmark
Requires-Dist: lm-eval<1.0.0,>=0.4.4; extra == 'benchmark'
Requires-Dist: optuna<5.0.0,>=4.0.0; extra == 'benchmark'
Provides-Extra: rl
Requires-Dist: gymnasium<2.0.0,>=1.0.0; extra == 'rl'
Requires-Dist: openai<3.0.0,>=2.0.0; extra == 'rl'
Requires-Dist: sb3-contrib<3.0.0,>=2.0.0; extra == 'rl'
Requires-Dist: stable-baselines3[extra]<3.0.0,>=2.0.0; extra == 'rl'
Requires-Dist: tenacity<9.1.2,>=9.0.0; extra == 'rl'
